ImageInsight/__init__.py
ImageInsight/main.py
ImageInsight/models.py
ImageInsight/utils.py
ImageInsight-0.2.1.dist-info/METADATA
ImageInsight-0.2.1.dist-info/WHEEL
ImageInsight-0.2.1.dist-info/entry_points.txt
ImageInsight-0.2.1.dist-info/top_level.txt
ImageInsight-0.2.1.dist-info/RECORD
