Metadata-Version: 2.1
Name: ImageInsight
Version: 0.2.1
Summary: A package to extract semantic activations from images using pre-trained models.
Home-page: https://github.com/yourusername/my_package
Author: Kinkini
Author-email: kinkinimonaragala@gmail.com
License: MIT License
Classifier: Programming Language :: Python :: 3
Classifier: License :: OSI Approved :: MIT License
Classifier: Operating System :: OS Independent
Requires-Python: >=3.6
Requires-Dist: Pillow
Requires-Dist: matplotlib
Requires-Dist: numpy
Requires-Dist: torch
Requires-Dist: torchvision
Requires-Dist: transformers
